reposcribe/__init__.py
reposcribe/cli.py
reposcribe/core.py
RepoScribe-0.2.6.dist-info/LICENSE
RepoScribe-0.2.6.dist-info/METADATA
RepoScribe-0.2.6.dist-info/WHEEL
RepoScribe-0.2.6.dist-info/entry_points.txt
RepoScribe-0.2.6.dist-info/top_level.txt
RepoScribe-0.2.6.dist-info/RECORD
