Metadata-Version: 2.1
Name: RepoScribe
Version: 0.2.6
Summary: A lightweight tool to compile project files and directories into a structured Markdown document
Home-page: https://github.com/reversehobo/RepoScribe
Author: Ruben Selander
Author-email: info@nordicintel.com
Classifier: Development Status :: 3 - Alpha
Classifier: Intended Audience :: Developers
Classifier: Topic :: Software Development :: Documentation
Classifier: License :: OSI Approved :: MIT License
Classifier: Programming Language :: Python :: 3
Requires-Python: >=3.10
License-File: LICENSE
